{"cameraMode":{"drawMode":0,"name":"Shaded","section":"Shading Mode"},"sceneLighting":false,"audioPlay":false,"sceneViewState":{"showFog":true,"showMaterialUpdate":false,"showSkybox":false,"showFlares":true,"showImageEffects":true,"showParticleSystems":true},"in2DMode":false,"pivot":{"x":-0.013921976089477539,"y":1.4872549772262574,"z":-3.003905773162842},"rotation":{"x":0.0010933869052678347,"y":-0.998744547367096,"z":0.04428272321820259,"w":0.024580474942922593},"size":2.8497302532196047,"orthographic":false}